flowter/__init__.py
flowter/helper.py
flowter/version.py
flowter-0.2.0.dist-info/LICENSE
flowter-0.2.0.dist-info/METADATA
flowter-0.2.0.dist-info/WHEEL
flowter-0.2.0.dist-info/RECORD
