Metadata-Version: 2.1
Name: flowter
Version: 0.2.0
Summary: 🌊 Flowter: Making your Python pipelines glide as effortlessly as an otter in water. 🦦
License: Apache-2.0
Author: Allen Chou
Author-email: f1470891079@gmail.com
Requires-Python: >=3.8.0,<3.12.0
Classifier: License :: OSI Approved :: Apache Software License
Classifier: Programming Language :: Python :: 3
Classifier: Programming Language :: Python :: 3.8
Classifier: Programming Language :: Python :: 3.9
Classifier: Programming Language :: Python :: 3.10
Classifier: Programming Language :: Python :: 3.11
Provides-Extra: dev
Requires-Dist: pytz
Requires-Dist: rich
Requires-Dist: typing-extensions
